somq/__init__.py
somq/message_queue.py
somq/test_message_queue.py
somq-0.1.5.dist-info/LICENSE
somq-0.1.5.dist-info/METADATA
somq-0.1.5.dist-info/WHEEL
somq-0.1.5.dist-info/top_level.txt
somq-0.1.5.dist-info/RECORD
