Metadata-Version: 2.1
Name: somq
Version: 0.1.5
Summary: Simple Object-based Message Queue
Author-email: Jackie Yang <jackie@jackieyang.me>
License: Apache License
Project-URL: Homepage, https://github.com/valkjsaaa/somq
Project-URL: Bug Tracker, https://github.com/valkjsaaa/somq/issues
Classifier: Development Status :: 3 - Alpha
Classifier: Intended Audience :: Developers
Classifier: Topic :: Software Development :: Libraries :: Python Modules
Classifier: License :: OSI Approved :: Apache Software License
Classifier: Programming Language :: Python :: 3.7
Classifier: Programming Language :: Python :: 3.8
Classifier: Programming Language :: Python :: 3.9
Classifier: Operating System :: OS Independent
Requires-Python: >=3.7
License-File: LICENSE
